hark_imagestore/__init__.py
hark_imagestore/cli.py
hark_imagestore/imagecache.py
hark_imagestore/server.py
hark_imagestore/lib/__init__.py
hark_imagestore/lib/aws.py
hark_imagestore/lib/server.py
hark_imagestore-1.0.0.dev4.dist-info/DESCRIPTION.rst
hark_imagestore-1.0.0.dev4.dist-info/METADATA
hark_imagestore-1.0.0.dev4.dist-info/RECORD
hark_imagestore-1.0.0.dev4.dist-info/WHEEL
hark_imagestore-1.0.0.dev4.dist-info/entry_points.txt
hark_imagestore-1.0.0.dev4.dist-info/metadata.json
hark_imagestore-1.0.0.dev4.dist-info/top_level.txt
hark_imagestore-1.0.0.dev4.dist-info/zip-safe
