Metadata-Version: 2.0
Name: hark-imagestore
Version: 1.0.0.dev4
Summary: image store service for the hark tool
Home-page: https://hark-project.net
Author: Cera Davies
Author-email: ceralena.davies@gmail.com
License: GNU Affero General Public License v3 (GPLv3)
Keywords: virtualization development OS
Platform: UNKNOWN
Classifier: Development Status :: 2 - Pre-Alpha
Classifier: Framework :: Pytest
Classifier: Intended Audience :: Developers
Classifier: Intended Audience :: Education
Classifier: Intended Audience :: Science/Research
Classifier: License :: OSI Approved :: GNU General Public License v3 (GPLv3)
Classifier: Natural Language :: English
Classifier: Operating System :: POSIX :: BSD :: FreeBSD
Classifier: Operating System :: POSIX :: Linux
Classifier: Operating System :: MacOS :: MacOS X
Classifier: Programming Language :: Python :: 3
Classifier: Programming Language :: Python :: 3 :: Only
Classifier: Programming Language :: Python :: 3.3
Classifier: Programming Language :: Python :: 3.4
Classifier: Programming Language :: Python :: 3.5
Requires-Dist: Flask (==0.11.1)
Requires-Dist: boto3 (==1.3.1)
Requires-Dist: click (==6.6)
Requires-Dist: gunicorn (==19.6.0)
Requires-Dist: hark (>=v1.0.0.dev2)
